diffaaable/__init__.py
diffaaable/adaptive.py
diffaaable/core.py
diffaaable/lorentz.py
diffaaable/selective.py
diffaaable/vectorial.py
diffaaable-1.1.0.dist-info/LICENSE
diffaaable-1.1.0.dist-info/WHEEL
diffaaable-1.1.0.dist-info/METADATA
diffaaable-1.1.0.dist-info/RECORD
