Metadata-Version: 2.3
Name: diffaaable
Version: 1.1.0
Summary: JAX-differentiable AAA algorithm
Keywords: python
Author-email: Jan David Fischbach <fischbach@kit.edu>
Requires-Python: >=3.9
Classifier: Programming Language :: Python :: 3.9
Classifier: Programming Language :: Python :: 3.10
Classifier: Programming Language :: Python :: 3.11
Classifier: Operating System :: OS Independent
Requires-Dist: numpy
Requires-Dist: jax
Requires-Dist: jaxlib
Requires-Dist: baryrat
Requires-Dist: jaxopt
Requires-Dist: tbump>=6.11.0 ; extra == "dev"
Requires-Dist: towncrier ; extra == "dev"
Requires-Dist: pre-commit ; extra == "dev"
Requires-Dist: pytest ; extra == "dev"
Requires-Dist: pytest-cov ; extra == "dev"
Requires-Dist: pytest_regressions ; extra == "dev"
Requires-Dist: pytest-benchmark ; extra == "dev"
Requires-Dist: matplotlib ; extra == "dev"
Requires-Dist: jupytext ; extra == "docs"
Requires-Dist: matplotlib ; extra == "docs"
Requires-Dist: jupyter-book ; extra == "docs"
Requires-Dist: sphinx_math_dollar ; extra == "docs"
Provides-Extra: dev
Provides-Extra: docs
